LICENSE.txt
MANIFEST.in
README.md
changelog.txt
setup.py
hass_configurator/__init__.py
hass_configurator/configurator.py
hass_configurator/dev.html
hass_configurator/flUhRq6tzZclQEJ-Vdg-IuiaDsNc.woff2
hass_configurator/jquery-3.6.0.min.js
hass_configurator/js-yaml.min.js
hass_configurator/material-icons.fallback.css
hass_configurator/materialize.min.js
hass_configurator/style.css
hass_configurator.egg-info/PKG-INFO
hass_configurator.egg-info/SOURCES.txt
hass_configurator.egg-info/dependency_links.txt
hass_configurator.egg-info/entry_points.txt
hass_configurator.egg-info/not-zip-safe
hass_configurator.egg-info/requires.txt
hass_configurator.egg-info/top_level.txt