Metadata-Version: 2.1
Name: hass-configurator
Version: 0.5.0
Summary: HASS Configurator
Home-page: http://github.com/danielperna84/hass-configurator
Author: Daniel Perna
Author-email: danielperna84@gmail.com
License: MIT
Download-URL: https://github.com/danielperna84/hass-configurator/tarball/0.5.0
Project-URL: Documentation, https://github.com/danielperna84/hass-configurator
Project-URL: Tracker, https://github.com/danielperna84/hass-configurator/issues
Keywords: home-assistant
Platform: any
Classifier: Programming Language :: Python :: 3
Classifier: Operating System :: OS Independent
Classifier: Topic :: Text Editors
Requires-Python: >=3
